pyassignment/__init__.py
pyassignment/cli.py
pyassignment/utils.py
pyassignment/actions/__init__.py
pyassignment/actions/build_blackboard_assignment.py
pyassignment/actions/build_pdf_assignment.py
pyassignment/actions/build_problem_set_and_blackboard_quiz.py
pyassignment/assignment/__init__.py
pyassignment/assignment/assignment.py
pyassignment/assignment/element.py
pyassignment/assignment/figure.py
pyassignment/assignment/information.py
pyassignment/assignment/question.py
pyassignment/assignment/answers/__init__.py
pyassignment/assignment/answers/answer.py
pyassignment/assignment/answers/answer_base.py
pyassignment/assignment/answers/essay.py
pyassignment/assignment/answers/file_response.py
pyassignment/assignment/answers/multiple_choice.py
pyassignment/assignment/answers/numerical.py
pyassignment/assignment/answers/text.py
pyassignment/filters/__init__.py
pyassignment/filters/predicates.py
pyassignment/filters/quiz_extractor.py
pyassignment/graders/__init__.py
pyassignment/graders/cl_grader.py
pyassignment/graders/grader_base.py
pyassignment/graders/python_test.py
pyassignment/graders/shell_test.py
pyassignment/graders/test.py
pyassignment/graders/utils.py
pyassignment/graders/writers.py
pyassignment/question_bank/__init__.py
pyassignment/question_bank/utils.py
pyassignment/readers/__init__.py
pyassignment/readers/json.py
pyassignment/readers/markdown.py
pyassignment/readers/reader_base.py
pyassignment/writers/__init__.py
pyassignment/writers/blackboard_quiz.py
pyassignment/writers/latex.py
pyassignment/writers/simple.py
pyassignment/writers/writer_base.py
pyassignment-2.1.6.dist-info/licenses/LICENSE.txt
pyassignment-2.1.6.dist-info/METADATA
pyassignment-2.1.6.dist-info/WHEEL
pyassignment-2.1.6.dist-info/entry_points.txt
pyassignment-2.1.6.dist-info/top_level.txt
pyassignment-2.1.6.dist-info/RECORD
