Metadata-Version: 2.4
Name: pyassignment
Version: 2.1.6
Summary: A python module for authoring and assessing homework assignments.
Requires-Python: >=3.8
License-File: LICENSE.txt
Requires-Dist: numpy>=1.24.1
Requires-Dist: pyparsing>=3.0.9
Requires-Dist: pint>=0.20.1
Requires-Dist: pylatex>=1.4.1
Requires-Dist: pyyaml>=6.0
Requires-Dist: macro-expander>=0.3
Requires-Dist: pyerrorprop>=3.1.2
Requires-Dist: typer>=0.9.0
Requires-Dist: jinja2>=3.1.2
Dynamic: license-file
